{
  "main": {
    "id": "4d225a17bba2906e",
    "type": "split",
    "children": [
      {
        "id": "d71f6550fcc70249",
        "type": "tabs",
        "children": [
          {
            "id": "6060b098ee9aa43c",
            "type": "leaf",
            "state": {
              "type": "markdown",
              "state": {
                "file": "Álgebra II/Subespacios.md",
                "mode": "preview",
                "source": true
              }
            }
          }
        ]
      }
    ],
    "direction": "vertical"
  },
  "left": {
    "id": "8c54ab5a1636753a",
    "type": "split",
    "children": [
      {
        "id": "95ee31ff2138f8f3",
        "type": "tabs",
        "children": [
          {
            "id": "8c1036a0b0a45e3e",
            "type": "leaf",
            "state": {
              "type": "file-explorer",
              "state": {
                "sortOrder": "alphabetical"
              }
            }
          },
          {
            "id": "178700d707526f5b",
            "type": "leaf",
            "state": {
              "type": "search",
              "state": {
                "query": "",
                "matchingCase": true,
                "explainSearch": true,
                "collapseAll": true,
                "extraContext": true,
                "sortOrder": "alphabetical"
              }
            }
          },
          {
            "id": "3a4e59fefdd05268",
            "type": "leaf",
            "state": {
              "type": "bookmarks",
              "state": {}
            }
          }
        ]
      }
    ],
    "direction": "horizontal",
    "width": 464.5
  },
  "right": {
    "id": "f19a445c27016a6e",
    "type": "split",
    "children": [
      {
        "id": "7f87df82da077ef0",
        "type": "tabs",
        "children": [
          {
            "id": "6b8c795d3756fc69",
            "type": "leaf",
            "state": {
              "type": "outline",
              "state": {
                "file": "Álgebra II/Subespacios.md"
              }
            }
          },
          {
            "id": "651e73bbbb50cca8",
            "type": "leaf",
            "state": {
              "type": "backlink",
              "state": {
                "file": "Álgebra II/Subespacios.md",
                "collapseAll": false,
                "extraContext": false,
                "sortOrder": "alphabetical",
                "showSearch": false,
                "searchQuery": "",
                "backlinkCollapsed": false,
                "unlinkedCollapsed": true
              }
            }
          },
          {
            "id": "1fbcdccf23391426",
            "type": "leaf",
            "state": {
              "type": "outgoing-link",
              "state": {
                "file": "Álgebra II/Subespacios.md",
                "linksCollapsed": false,
                "unlinkedCollapsed": true
              }
            }
          },
          {
            "id": "ca89ba698f4b3e61",
            "type": "leaf",
            "state": {
              "type": "tag",
              "state": {
                "sortOrder": "frequency",
                "useHierarchy": false
              }
            }
          },
          {
            "id": "8e3870351fe83571",
            "type": "leaf",
            "state": {
              "type": "advanced-tables-toolbar",
              "state": {}
            }
          }
        ],
        "currentTab": 1
      }
    ],
    "direction": "horizontal",
    "width": 392.5,
    "collapsed": true
  },
  "left-ribbon": {
    "hiddenItems": {
      "audio-recorder:Start/stop recording": false,
      "switcher:Open quick switcher": false,
      "graph:Open graph view": false,
      "canvas:Create new canvas": false,
      "daily-notes:Open today's daily note": false,
      "templates:Insert template": false,
      "command-palette:Open command palette": false,
      "obsidian-focus-mode:Toggle Focus Mode (Shift + Click to show active pane only)": false
    }
  },
  "active": "6060b098ee9aa43c",
  "lastOpenFiles": [
    "Álgebra II/Subespacios de Matriz.md",
    "Álgebra II/Transformaciones Lineales.md",
    "Álgebra II/Subespacios.md",
    "Álgebra II/Sistemas de E D Homogéneas.md",
    "Álgebra II/Producto Interno.md",
    "Álgebra II/Ortogonalidad.md",
    "Álgebra II/Operaciones entre Subespacios.md",
    "Álgebra II/Método de Gram-Schmidt.md",
    "Álgebra II/Matrices Normales.md",
    "Álgebra II/Formas Cuadráticas.md",
    "Álgebra II/Espacios Vectoriales.md",
    "Álgebra II/Ejemplos de Transformaciones Lineales.md",
    "Álgebra II/Ecuaciones Diferenciales Ordinarias.md",
    "Álgebra II/Descomposición en Valores Singulares.md",
    "Álgebra II/Coordenadas.md",
    "Álgebra II/Autovalores y Autovectores.md",
    "Álgebra II/Álgebra II.md",
    "Álgebra II/Álgebra II.pdf",
    "Álgebra II/Formas Cuadráticas.pdf",
    "Introducción a Sistemas Distribuidos/Breaking WEP.md",
    "Matemática Discreta/Álgebra de Boole.md",
    "Introducción a Sistemas Distribuidos/Application Layer/Electronic Mail in the Internet.md",
    "Sistemas Operativos/API de Threads.md",
    "Análisis de la Información/Web Rest API.md",
    "Análisis de la Información/Verificar y Validar requerimientos.md",
    "Modelos y Optimización I/Variables Enteras.md",
    "Análisis de la Información/Técnicas de Descubrimiento de Requisitos.md",
    "Análisis de la Información/Técnicas de Análisis, Modelado y Especificación.md",
    "Introducción a Sistemas Distribuidos/Breaking WEP.pdf",
    "Introducción a Sistemas Distribuidos/Breaking WEP.tex",
    "Indice.pdf",
    "Indice.tex",
    "Untitled.canvas",
    "Análisis de la Información/Attachments/Casos de Uso 1.png",
    "Análisis Matemático II/Attachments/Cuadricas 1.png",
    "Física II/Attachments/Potencia Activa y Reactiva 2.svg",
    "Física II/Attachments/Potencia Activa y Reactiva 1.svg",
    "Física II/Attachments/Final 1.png",
    "Matemática Discreta/Attachments/Algoritmos 1.png",
    "Algoritmos I/Attachments/Recursividad 1.png",
    "Análisis de la Información/Attachments/Casos de Uso 3.png",
    "Introducción a Sistemas Distribuidos/Attachments/Cellular Internet Access 2.png",
    "Física II/Attachments/Tercer Parcial 1.svg",
    "Base de Datos",
    "Algoritmos II/Attachments/Machete - AAB.pdf"
  ]
}